{
    "fluentMethods": true,
    "relationships": [
        {
            "relationshipName": "booking",
            "otherEntityName": "booking",
            "relationshipType": "many-to-one",
            "otherEntityField": "id"
        }
    ],
    "fields": [
        {
            "fieldName": "roomName",
            "fieldType": "String",
            "fieldValidateRules": [
                "required"
            ]
        },
        {
            "fieldName": "roomType",
            "fieldType": "RoomType",
            "fieldValues": "AC,NON_AC",
            "fieldValidateRules": [
                "required"
            ]
        }
    ],
    "changelogDate": "20171216051618",
    "entityTableName": "room",
    "dto": "mapstruct",
    "pagination": "infinite-scroll",
    "service": "serviceImpl",
    "jpaMetamodelFiltering": false,
    "angularJSSuffix": "mySuffix"
}